sharded/__init__.py
sharded_manager-0.0.1.dist-info/LICENSE
sharded_manager-0.0.1.dist-info/METADATA
sharded_manager-0.0.1.dist-info/WHEEL
sharded_manager-0.0.1.dist-info/RECORD
