Metadata-Version: 2.1
Name: sharded-manager
Version: 0.0.1
Summary: JSON File handler for creating and managing configuration files, data files, and more.
License: MIT
Author: Adam Garza
Author-email: adriftible@gmail.com
Requires-Python: >=3.8,<4.0
Classifier: License :: OSI Approved :: MIT License
Classifier: Programming Language :: Python :: 3
Classifier: Programming Language :: Python :: 3.8
Classifier: Programming Language :: Python :: 3.9
Classifier: Programming Language :: Python :: 3.10
Classifier: Programming Language :: Python :: 3.11
Classifier: Programming Language :: Python :: 3.12
